mypyrun.py
mypy_runner-0.6.0.dist-info/METADATA
mypy_runner-0.6.0.dist-info/WHEEL
mypy_runner-0.6.0.dist-info/entry_points.txt
mypy_runner-0.6.0.dist-info/RECORD
