Metadata-Version: 2.1
Name: mypy-runner
Version: 0.6.0
Summary: Run mypy with options to filter errors and colorize output
Home-page: https://github.com/chadrik/mypy-runner
License: MIT
Keywords: pep484,typing,annotations,mypy
Author: Chad Dombrova
Author-email: chadrik@gmail.com
Classifier: Development Status :: 5 - Production/Stable
Classifier: Intended Audience :: Developers
Classifier: License :: OSI Approved :: MIT License
Classifier: Programming Language :: Python :: 2
Classifier: Programming Language :: Python :: 2.7
Classifier: Programming Language :: Python :: 3
Classifier: Programming Language :: Python :: 3.4
Classifier: Programming Language :: Python :: 3.5
Classifier: Programming Language :: Python :: 3.6
Classifier: Programming Language :: Python :: 3.7
Classifier: Programming Language :: Python :: 3.8
Classifier: Programming Language :: Python :: 3.9
Classifier: Programming Language :: Python :: 3.10
Classifier: Programming Language :: Python :: 3.11
Classifier: Programming Language :: Python :: 2
Classifier: Programming Language :: Python :: 2.7
Classifier: Programming Language :: Python :: 3
Classifier: Programming Language :: Python :: 3.6
Classifier: Programming Language :: Python :: 3.7
Classifier: Topic :: Software Development :: Build Tools
Provides-Extra: tests
Requires-Dist: configparser
Requires-Dist: coverage ; extra == "tests"
Requires-Dist: pytest (>=6.1,<7.0) ; extra == "tests"
Project-URL: Repository, https://github.com/chadrik/mypy-runner
